deepnlp/__init__.py
deepnlp/constant.py
deepnlp/inference_pipeline.py
deepnlp/preprocess_load.py
deepnlp/utils/__init__.py
deepnlp/utils/data_struct.py
deepnlp/utils/print_out.py
deepnlp/utils/tokenizer.py
deepnlp_cerelab-1.0.2.dist-info/LICENSE
deepnlp_cerelab-1.0.2.dist-info/METADATA
deepnlp_cerelab-1.0.2.dist-info/WHEEL
deepnlp_cerelab-1.0.2.dist-info/top_level.txt
deepnlp_cerelab-1.0.2.dist-info/RECORD
