Metadata-Version: 2.1
Name: deepnlp-cerelab
Version: 1.0.2
Summary: Natural language processing package based on modern deep learning methods
Home-page: https://github.com/hieupth/deepnlp
Author: Dat Tien Nguyen and Hieu Trung Pham
Author-email: nduc0231@gmail.com
Maintainer: Dat Tien Nguyen
Maintainer-email: nduc0231@gmail.com
License: UNKNOWN
Keywords: deepnlp
Platform: UNKNOWN
Classifier: Development Status :: 3 - Alpha
Classifier: Intended Audience :: Developers
Classifier: Programming Language :: Python :: 3.7
Classifier: License :: OSI Approved :: Apache Software License
Classifier: Operating System :: OS Independent
Requires-Python: >=3.7
License-File: LICENSE
Requires-Dist: transformers (>=4.21.3)
Requires-Dist: tensorflow (>=2.8.2)
Requires-Dist: numpy
Requires-Dist: gdown (>=4.4.0)
